{"credit":"Made with Blockbench","texture_size":[32,32],"textures":{"0":"mvndicraft:blacksmith/hot_steel_generic","particle":"mvndicraft:blacksmith/hot_steel_generic"},"elements":[{"from":[7.5,6,-7.5],"to":[8.5,7,23.5],"rotation":{"angle":0,"axis":"y","origin":[7.5,7,3.5]},"faces":{"north":{"uv":[0.5,1,1,1.5],"texture":"#0"},"east":{"uv":[0.5,5,16,5.5],"texture":"#0"},"south":{"uv":[4,0.5,4.5,1],"texture":"#0"},"west":{"uv":[0.5,4,16,4.5],"texture":"#0"},"up":{"uv":[0.5,4.5,16,5],"rotation":90,"texture":"#0"}}}],"display":{"fixed":{"rotation":[-90,0,0],"translation":[0,0,-1.75],"scale":[0.89063,0.89063,0.89063]}}}