{
	"credit": "Made with Blockbench",
	"textures": {
		"0": "mvndicraft:ui/mill/mill",
		"particle": "mvndicraft:ui/mill/mill"
	},
	"elements": [
		{
			"from": [0, 0, 0],
			"to": [16, 16, 0],
			"faces": {
				"north": {"uv": [0, 0, 14.75, 14.75], "texture": "#0"},
				"east": {"uv": [0, 0, 0, 16], "texture": "#missing"},
				"west": {"uv": [0, 0, 0, 16], "texture": "#missing"},
				"up": {"uv": [0, 0, 16, 0], "texture": "#missing"},
				"down": {"uv": [0, 0, 16, 0], "texture": "#missing"}
			}
		}
	],
	"gui_light": "front",
	"display": {
		"thirdperson_righthand": {
			"scale": [0, 0, 0]
		},
		"firstperson_righthand": {
			"scale": [0, 0, 0]
		},
		"gui": {
			"rotation": [0, 180, 0],
			"translation": [0, 0.5, 0],
			"scale": [3.89453, 3.67773, 3.4668]
		}
	}
}